switch_java/__init__.py
switch_java/main.py
switch_java_version-0.1.0.dist-info/LICENSE
switch_java_version-0.1.0.dist-info/METADATA
switch_java_version-0.1.0.dist-info/WHEEL
switch_java_version-0.1.0.dist-info/entry_points.txt
switch_java_version-0.1.0.dist-info/top_level.txt
switch_java_version-0.1.0.dist-info/RECORD
