Metadata-Version: 2.1
Name: switch-java-version
Version: 0.1.0
Summary: A script to switch between Java versions on Windows
Home-page: https://github.com/yourusername/switch-java
Author: Gamertoky1188
Author-email: your.email@example.com
Classifier: Programming Language :: Python :: 3
Classifier: License :: OSI Approved :: MIT License
Classifier: Operating System :: Microsoft :: Windows
Requires-Python: >=3.6
License-File: LICENSE
